keyring_wsl_client-0.1.8.dist-info/METADATA
keyring_wsl_client-0.1.8.dist-info/WHEEL
keyring_wsl_client-0.1.8.dist-info/entry_points.txt
keyring_wsl_client/__init__.py
keyring_wsl_client-0.1.8.dist-info/RECORD
