Metadata-Version: 2.1
Name: keyring-wsl-client
Version: 0.1.8
Summary: Keyring proxy for wsl (client part)
Author-Email: Kalle M. Aagaard <git@k-moeller.dk>
License: MIT
Project-URL: Repository, https://github.com/KalleDK/py-keyring-wsl-guest
Requires-Python: >=3.10
Requires-Dist: keyring>=24.2.0
